Metadata-Version: 2.1
Name: erdgen
Version: 0.1.1
Summary: Generate a DBML ERD from DBT YML relationships
Home-page: https://github.com/neo-andrew-moss/erdgen
Author: Andrew Moss
Author-email: andrew.moss@neofinancial.com
License: MIT license
Platform: UNKNOWN
Classifier: Development Status :: 3 - Alpha
Classifier: Intended Audience :: Developers
Classifier: License :: OSI Approved :: MIT License
Classifier: Natural Language :: English
Classifier: Programming Language :: Python :: 3
Requires-Python: >=3.6
License-File: LICENSE
